myapp/__init__.py
plup_hello-0.4.2.dist-info/METADATA
plup_hello-0.4.2.dist-info/WHEEL
plup_hello-0.4.2.dist-info/entry_points.txt
plup_hello-0.4.2.dist-info/top_level.txt
plup_hello-0.4.2.dist-info/RECORD
