Metadata-Version: 2.1
Name: plup-hello
Version: 0.4.2
Summary: StartinBlox test package
Home-page: UNKNOWN
Author: UNKNOWN
Author-email: UNKNOWN
License: MIT
Platform: UNKNOWN
Classifier: Programming Language :: Python :: 3
Classifier: Programming Language :: Python :: 3.5
